langgraph_distributed_agent/__init__.py
langgraph_distributed_agent/agent_cli.py
langgraph_distributed_agent/agent_client.py
langgraph_distributed_agent/agent_runner.py
langgraph_distributed_agent/distributed_agent_worker.py
langgraph_distributed_agent/redis_lock.py
langgraph_distributed_agent/robust_aiomysql_saver.py
langgraph_distributed_agent/utils.py
langgraph_distributed_agent-0.1.4.dist-info/licenses/LICENSE
langgraph_distributed_agent-0.1.4.dist-info/METADATA
langgraph_distributed_agent-0.1.4.dist-info/WHEEL
langgraph_distributed_agent-0.1.4.dist-info/top_level.txt
langgraph_distributed_agent-0.1.4.dist-info/RECORD
