Metadata-Version: 2.4
Name: langgraph_distributed_agent
Version: 0.1.4
Summary: Huya AIOps Agent SDK
Author-email: panjianning <panjianning@huya.com>, lanxuanli <lanxuanli@huya.com>
License: MIT
Requires-Python: >=3.10
License-File: LICENSE
Requires-Dist: requests
Requires-Dist: redis
Requires-Dist: httpx
Requires-Dist: langchain
Requires-Dist: langgraph
Requires-Dist: langchain-openai
Requires-Dist: langgraph-checkpoint-sqlite
Requires-Dist: langchain-mcp-adapters
Requires-Dist: aiosqlite
Requires-Dist: langgraph-checkpoint-redis
Requires-Dist: pydantic
Requires-Dist: pydantic-settings
Requires-Dist: langgraph-checkpoint-mysql[aiomysql]
Requires-Dist: fastmcp
Requires-Dist: typing-extensions
Requires-Dist: python-dotenv
Requires-Dist: colorama
Dynamic: license-file
